geniepy/__init__.py
geniepy/config.py
geniepy/config.yaml
geniepy/errors.py
geniepy/pubmed.py
geniepy/classmgmt/__init__.py
geniepy/classmgmt/classifiers.py
geniepy/classmgmt/classmgr.py
geniepy/datamgmt/__init__.py
geniepy/datamgmt/daomanager.py
geniepy/datamgmt/daos.py
geniepy/datamgmt/parsers.py
geniepy/datamgmt/repositories.py
geniepy/datamgmt/scrapers.py
geniepy/datamgmt/tables.py
geniepy/scripts/author-data.py
geniepy/scripts/citation_cloud_function.py
geniepy/scripts/citation_historical.py
geniepy/scripts/geniebootsrap.py
geniepy/scripts/genieutils.py
geniepy/scripts/issn_historical.py
geniepy/scripts/pubmed_historical.py
geniepy-0.16.dist-info/AUTHORS.rst
geniepy-0.16.dist-info/LICENSE.txt
geniepy-0.16.dist-info/METADATA
geniepy-0.16.dist-info/WHEEL
geniepy-0.16.dist-info/entry_points.txt
geniepy-0.16.dist-info/top_level.txt
geniepy-0.16.dist-info/RECORD
