Metadata-Version: 2.1
Name: geniepy
Version: 0.16
Summary: Gene-Disease relationship trend detection
Home-page: https://github.com/derekkinzo/genie
Author: The Harvard LAMP Team
Maintainer: Derek Kinzo
Maintainer-email: dhk891@g.harvard.edu
License: mit
Project-URL: Documentation, https://geniepy.readthedocs.io/en/latest/
Platform: any
Classifier: Development Status :: 4 - Beta
Classifier: Programming Language :: Python
Requires-Python: >=3.7,!=2.*
Requires-Dist: numpy
Requires-Dist: scipy
Requires-Dist: jsonlines
Requires-Dist: pandas
Requires-Dist: pandas-schema
Requires-Dist: pandas-gbq
Requires-Dist: sqlalchemy
Requires-Dist: pyyaml
Requires-Dist: googledrivedownloader
Requires-Dist: joblib
Requires-Dist: sklearn
Requires-Dist: tqdm
Requires-Dist: wget
Provides-Extra: testing
Requires-Dist: pytest ; extra == 'testing'
Requires-Dist: pytest-cov ; extra == 'testing'
